awslabs/__init__.py
awslabs/amazon_mq_mcp_server/__init__.py
awslabs/amazon_mq_mcp_server/aws_service_mcp_generator.py
awslabs/amazon_mq_mcp_server/consts.py
awslabs/amazon_mq_mcp_server/server.py
awslabs/amazon_mq_mcp_server/rabbitmq/__init__.py
awslabs/amazon_mq_mcp_server/rabbitmq/admin.py
awslabs/amazon_mq_mcp_server/rabbitmq/connection.py
awslabs/amazon_mq_mcp_server/rabbitmq/handlers.py
awslabs/amazon_mq_mcp_server/rabbitmq/module.py
awslabs/amazon_mq_mcp_server/rabbitmq/doc/rabbitmq_broker_sizing_guide.md
awslabs/amazon_mq_mcp_server/rabbitmq/doc/rabbitmq_performance_optimization_best_practice.md
awslabs/amazon_mq_mcp_server/rabbitmq/doc/rabbitmq_production_deployment_guidelines.md
awslabs/amazon_mq_mcp_server/rabbitmq/doc/rabbitmq_quorum_queue_migration_guide.md
awslabs/amazon_mq_mcp_server/rabbitmq/doc/rabbitmq_setup_best_practice.md
awslabs_amazon_mq_mcp_server-2.0.15.dist-info/METADATA
awslabs_amazon_mq_mcp_server-2.0.15.dist-info/WHEEL
awslabs_amazon_mq_mcp_server-2.0.15.dist-info/entry_points.txt
awslabs_amazon_mq_mcp_server-2.0.15.dist-info/licenses/LICENSE
awslabs_amazon_mq_mcp_server-2.0.15.dist-info/licenses/NOTICE
awslabs_amazon_mq_mcp_server-2.0.15.dist-info/RECORD
